{
  "annotations": {
    "list": [
      {
        "builtIn": 1,
        "datasource": "-- Grafana --",
        "enable": true,
        "hide": true,
        "iconColor": "rgba(0, 211, 255, 1)",
        "name": "Annotations & Alerts",
        "type": "dashboard"
      }
    ]
  },
  "editable": true,
  "fiscalYearStartMonth": 0,
  "graphTooltip": 0,
  "id": null,
  "links": [],
  "liveNow": false,
  "panels": [
    {
      "collapsed": false,
      "gridPos": {"h": 1, "w": 24, "x": 0, "y": 0},
      "id": 100,
      "panels": [],
      "title": "Cost Overview",
      "type": "row"
    },
    {
      "datasource": {"type": "prometheus", "uid": "prometheus"},
      "fieldConfig": {
        "defaults": {
          "color": {"mode": "thresholds"},
          "mappings": [],
          "thresholds": {
            "mode": "absolute",
            "steps": [
              {"color": "green", "value": null}
            ]
          },
          "unit": "currencyUSD"
        },
        "overrides": []
      },
      "gridPos": {"h": 4, "w": 6, "x": 0, "y": 1},
      "id": 1,
      "options": {
        "colorMode": "value",
        "graphMode": "none",
        "justifyMode": "auto",
        "orientation": "auto",
        "reduceOptions": {
          "calcs": ["lastNotNull"],
          "fields": "",
          "values": false
        },
        "textMode": "value_and_name"
      },
      "pluginVersion": "10.0.0",
      "targets": [
        {
          "expr": "sum(omniphi_billing_monthly_cost)",
          "legendFormat": "Monthly Total",
          "refId": "A"
        }
      ],
      "title": "Monthly Cost (Current)",
      "type": "stat"
    },
    {
      "datasource": {"type": "prometheus", "uid": "prometheus"},
      "fieldConfig": {
        "defaults": {
          "color": {"mode": "thresholds"},
          "mappings": [],
          "thresholds": {
            "mode": "absolute",
            "steps": [
              {"color": "green", "value": null}
            ]
          },
          "unit": "currencyUSD"
        },
        "overrides": []
      },
      "gridPos": {"h": 4, "w": 6, "x": 6, "y": 1},
      "id": 2,
      "options": {
        "colorMode": "value",
        "graphMode": "area",
        "justifyMode": "auto",
        "orientation": "auto",
        "reduceOptions": {
          "calcs": ["lastNotNull"],
          "fields": "",
          "values": false
        },
        "textMode": "value_and_name"
      },
      "pluginVersion": "10.0.0",
      "targets": [
        {
          "expr": "sum(omniphi_billing_projected_cost)",
          "legendFormat": "Projected",
          "refId": "A"
        }
      ],
      "title": "Projected Monthly Cost",
      "type": "stat"
    },
    {
      "datasource": {"type": "prometheus", "uid": "prometheus"},
      "fieldConfig": {
        "defaults": {
          "color": {"mode": "thresholds"},
          "mappings": [],
          "thresholds": {
            "mode": "absolute",
            "steps": [
              {"color": "green", "value": null}
            ]
          },
          "unit": "currencyUSD"
        },
        "overrides": []
      },
      "gridPos": {"h": 4, "w": 6, "x": 12, "y": 1},
      "id": 3,
      "options": {
        "colorMode": "value",
        "graphMode": "none",
        "justifyMode": "auto",
        "orientation": "auto",
        "reduceOptions": {
          "calcs": ["mean"],
          "fields": "",
          "values": false
        },
        "textMode": "value_and_name"
      },
      "pluginVersion": "10.0.0",
      "targets": [
        {
          "expr": "avg(omniphi_billing_cost_per_validator)",
          "legendFormat": "Avg per Validator",
          "refId": "A"
        }
      ],
      "title": "Avg Cost per Validator",
      "type": "stat"
    },
    {
      "datasource": {"type": "prometheus", "uid": "prometheus"},
      "fieldConfig": {
        "defaults": {
          "color": {"mode": "thresholds"},
          "mappings": [],
          "thresholds": {
            "mode": "absolute",
            "steps": [
              {"color": "green", "value": null}
            ]
          }
        },
        "overrides": []
      },
      "gridPos": {"h": 4, "w": 6, "x": 18, "y": 1},
      "id": 4,
      "options": {
        "colorMode": "value",
        "graphMode": "none",
        "justifyMode": "auto",
        "orientation": "auto",
        "reduceOptions": {
          "calcs": ["lastNotNull"],
          "fields": "",
          "values": false
        },
        "textMode": "value_and_name"
      },
      "pluginVersion": "10.0.0",
      "targets": [
        {
          "expr": "count(omniphi_billing_active_subscription == 1)",
          "legendFormat": "Active Subscriptions",
          "refId": "A"
        }
      ],
      "title": "Active Subscriptions",
      "type": "stat"
    },
    {
      "collapsed": false,
      "gridPos": {"h": 1, "w": 24, "x": 0, "y": 5},
      "id": 101,
      "panels": [],
      "title": "Cost by Region",
      "type": "row"
    },
    {
      "datasource": {"type": "prometheus", "uid": "prometheus"},
      "fieldConfig": {
        "defaults": {
          "color": {"mode": "palette-classic"},
          "custom": {
            "hideFrom": {"legend": false, "tooltip": false, "viz": false}
          },
          "mappings": [],
          "unit": "currencyUSD"
        },
        "overrides": []
      },
      "gridPos": {"h": 8, "w": 8, "x": 0, "y": 6},
      "id": 10,
      "options": {
        "legend": {"displayMode": "list", "placement": "right"},
        "pieType": "donut",
        "reduceOptions": {
          "calcs": ["lastNotNull"],
          "fields": "",
          "values": false
        },
        "tooltip": {"mode": "single", "sort": "none"}
      },
      "pluginVersion": "10.0.0",
      "targets": [
        {
          "expr": "sum by (region) (omniphi_billing_monthly_cost)",
          "legendFormat": "{{region}}",
          "refId": "A"
        }
      ],
      "title": "Cost Distribution by Region",
      "type": "piechart"
    },
    {
      "datasource": {"type": "prometheus", "uid": "prometheus"},
      "fieldConfig": {
        "defaults": {
          "color": {"mode": "palette-classic"},
          "custom": {
            "hideFrom": {"legend": false, "tooltip": false, "viz": false}
          },
          "mappings": [],
          "unit": "currencyUSD"
        },
        "overrides": []
      },
      "gridPos": {"h": 8, "w": 8, "x": 8, "y": 6},
      "id": 11,
      "options": {
        "legend": {"displayMode": "list", "placement": "right"},
        "pieType": "donut",
        "reduceOptions": {
          "calcs": ["lastNotNull"],
          "fields": "",
          "values": false
        },
        "tooltip": {"mode": "single", "sort": "none"}
      },
      "pluginVersion": "10.0.0",
      "targets": [
        {
          "expr": "sum by (tier) (omniphi_billing_monthly_cost)",
          "legendFormat": "{{tier}}",
          "refId": "A"
        }
      ],
      "title": "Cost Distribution by Tier",
      "type": "piechart"
    },
    {
      "datasource": {"type": "prometheus", "uid": "prometheus"},
      "fieldConfig": {
        "defaults": {
          "color": {"mode": "thresholds"},
          "mappings": [],
          "thresholds": {
            "mode": "absolute",
            "steps": [
              {"color": "blue", "value": null}
            ]
          },
          "unit": "currencyUSD"
        },
        "overrides": []
      },
      "gridPos": {"h": 8, "w": 8, "x": 16, "y": 6},
      "id": 12,
      "options": {
        "displayMode": "lcd",
        "minVizHeight": 10,
        "minVizWidth": 0,
        "orientation": "horizontal",
        "reduceOptions": {
          "calcs": ["lastNotNull"],
          "fields": "",
          "values": false
        },
        "showUnfilled": true
      },
      "pluginVersion": "10.0.0",
      "targets": [
        {
          "expr": "sum by (provider) (omniphi_billing_monthly_cost)",
          "legendFormat": "{{provider}}",
          "refId": "A"
        }
      ],
      "title": "Cost by Provider",
      "type": "bargauge"
    },
    {
      "collapsed": false,
      "gridPos": {"h": 1, "w": 24, "x": 0, "y": 14},
      "id": 102,
      "panels": [],
      "title": "Cost Trends",
      "type": "row"
    },
    {
      "datasource": {"type": "prometheus", "uid": "prometheus"},
      "fieldConfig": {
        "defaults": {
          "color": {"mode": "palette-classic"},
          "custom": {
            "axisCenteredZero": false,
            "axisColorMode": "text",
            "axisLabel": "",
            "axisPlacement": "auto",
            "barAlignment": 0,
            "drawStyle": "line",
            "fillOpacity": 20,
            "gradientMode": "opacity",
            "hideFrom": {"legend": false, "tooltip": false, "viz": false},
            "lineInterpolation": "smooth",
            "lineWidth": 2,
            "pointSize": 5,
            "scaleDistribution": {"type": "linear"},
            "showPoints": "never",
            "spanNulls": false,
            "stacking": {"group": "A", "mode": "none"},
            "thresholdsStyle": {"mode": "off"}
          },
          "mappings": [],
          "thresholds": {
            "mode": "absolute",
            "steps": [
              {"color": "green", "value": null}
            ]
          },
          "unit": "currencyUSD"
        },
        "overrides": []
      },
      "gridPos": {"h": 8, "w": 12, "x": 0, "y": 15},
      "id": 20,
      "options": {
        "legend": {"calcs": ["mean", "sum"], "displayMode": "table", "placement": "bottom"},
        "tooltip": {"mode": "multi", "sort": "desc"}
      },
      "pluginVersion": "10.0.0",
      "targets": [
        {
          "expr": "sum(omniphi_billing_monthly_cost)",
          "legendFormat": "Total Cost",
          "refId": "A"
        }
      ],
      "title": "Monthly Cost Trend",
      "type": "timeseries"
    },
    {
      "datasource": {"type": "prometheus", "uid": "prometheus"},
      "fieldConfig": {
        "defaults": {
          "color": {"mode": "palette-classic"},
          "custom": {
            "axisCenteredZero": false,
            "axisColorMode": "text",
            "axisLabel": "",
            "axisPlacement": "auto",
            "barAlignment": 0,
            "drawStyle": "line",
            "fillOpacity": 20,
            "gradientMode": "opacity",
            "hideFrom": {"legend": false, "tooltip": false, "viz": false},
            "lineInterpolation": "smooth",
            "lineWidth": 2,
            "pointSize": 5,
            "scaleDistribution": {"type": "linear"},
            "showPoints": "never",
            "spanNulls": false,
            "stacking": {"group": "A", "mode": "normal"},
            "thresholdsStyle": {"mode": "off"}
          },
          "mappings": [],
          "thresholds": {
            "mode": "absolute",
            "steps": [
              {"color": "green", "value": null}
            ]
          },
          "unit": "currencyUSD"
        },
        "overrides": []
      },
      "gridPos": {"h": 8, "w": 12, "x": 12, "y": 15},
      "id": 21,
      "options": {
        "legend": {"calcs": ["mean", "sum"], "displayMode": "table", "placement": "bottom"},
        "tooltip": {"mode": "multi", "sort": "desc"}
      },
      "pluginVersion": "10.0.0",
      "targets": [
        {
          "expr": "sum by (region) (omniphi_billing_monthly_cost)",
          "legendFormat": "{{region}}",
          "refId": "A"
        }
      ],
      "title": "Cost by Region Over Time",
      "type": "timeseries"
    },
    {
      "collapsed": false,
      "gridPos": {"h": 1, "w": 24, "x": 0, "y": 23},
      "id": 103,
      "panels": [],
      "title": "Revenue & Payments",
      "type": "row"
    },
    {
      "datasource": {"type": "prometheus", "uid": "prometheus"},
      "fieldConfig": {
        "defaults": {
          "color": {"mode": "thresholds"},
          "mappings": [],
          "thresholds": {
            "mode": "absolute",
            "steps": [
              {"color": "green", "value": null}
            ]
          },
          "unit": "currencyUSD"
        },
        "overrides": []
      },
      "gridPos": {"h": 6, "w": 6, "x": 0, "y": 24},
      "id": 30,
      "options": {
        "colorMode": "value",
        "graphMode": "area",
        "justifyMode": "auto",
        "orientation": "auto",
        "reduceOptions": {
          "calcs": ["sum"],
          "fields": "",
          "values": false
        },
        "textMode": "value_and_name"
      },
      "pluginVersion": "10.0.0",
      "targets": [
        {
          "expr": "sum(increase(omniphi_billing_payment_received[30d]))",
          "legendFormat": "Revenue (30d)",
          "refId": "A"
        }
      ],
      "title": "Revenue (30d)",
      "type": "stat"
    },
    {
      "datasource": {"type": "prometheus", "uid": "prometheus"},
      "fieldConfig": {
        "defaults": {
          "color": {"mode": "thresholds"},
          "mappings": [],
          "thresholds": {
            "mode": "absolute",
            "steps": [
              {"color": "green", "value": null},
              {"color": "red", "value": 1}
            ]
          }
        },
        "overrides": []
      },
      "gridPos": {"h": 6, "w": 6, "x": 6, "y": 24},
      "id": 31,
      "options": {
        "colorMode": "background",
        "graphMode": "none",
        "justifyMode": "auto",
        "orientation": "auto",
        "reduceOptions": {
          "calcs": ["lastNotNull"],
          "fields": "",
          "values": false
        },
        "textMode": "value_and_name"
      },
      "pluginVersion": "10.0.0",
      "targets": [
        {
          "expr": "count(omniphi_billing_payment_failed == 1)",
          "legendFormat": "Failed Payments",
          "refId": "A"
        }
      ],
      "title": "Failed Payments",
      "type": "stat"
    },
    {
      "datasource": {"type": "prometheus", "uid": "prometheus"},
      "fieldConfig": {
        "defaults": {
          "color": {"mode": "palette-classic"},
          "custom": {
            "hideFrom": {"legend": false, "tooltip": false, "viz": false}
          },
          "mappings": []
        },
        "overrides": []
      },
      "gridPos": {"h": 6, "w": 6, "x": 12, "y": 24},
      "id": 32,
      "options": {
        "legend": {"displayMode": "list", "placement": "right"},
        "pieType": "donut",
        "reduceOptions": {
          "calcs": ["sum"],
          "fields": "",
          "values": false
        },
        "tooltip": {"mode": "single", "sort": "none"}
      },
      "pluginVersion": "10.0.0",
      "targets": [
        {
          "expr": "sum by (method) (increase(omniphi_billing_payment_received[30d]))",
          "legendFormat": "{{method}}",
          "refId": "A"
        }
      ],
      "title": "Payment Methods (30d)",
      "type": "piechart"
    },
    {
      "datasource": {"type": "prometheus", "uid": "prometheus"},
      "fieldConfig": {
        "defaults": {
          "color": {"mode": "thresholds"},
          "mappings": [],
          "thresholds": {
            "mode": "absolute",
            "steps": [
              {"color": "green", "value": null}
            ]
          },
          "unit": "currencyUSD"
        },
        "overrides": []
      },
      "gridPos": {"h": 6, "w": 6, "x": 18, "y": 24},
      "id": 33,
      "options": {
        "colorMode": "value",
        "graphMode": "none",
        "justifyMode": "auto",
        "orientation": "auto",
        "reduceOptions": {
          "calcs": ["lastNotNull"],
          "fields": "",
          "values": false
        },
        "textMode": "value_and_name"
      },
      "pluginVersion": "10.0.0",
      "targets": [
        {
          "expr": "sum(omniphi_billing_outstanding_balance)",
          "legendFormat": "Outstanding",
          "refId": "A"
        }
      ],
      "title": "Outstanding Balance",
      "type": "stat"
    }
  ],
  "refresh": "5m",
  "schemaVersion": 38,
  "style": "dark",
  "tags": ["omniphi", "billing", "cost"],
  "templating": {"list": []},
  "time": {"from": "now-30d", "to": "now"},
  "timepicker": {},
  "timezone": "browser",
  "title": "Omniphi Cost Dashboard",
  "uid": "omniphi-cost",
  "version": 1,
  "weekStart": ""
}
